Metadata-Version: 2.4
Name: quantaxis_pubsub-lance
Version: 1.19
Summary: QUANTAXIS PUBSUB:QUANTAXIS PUB/SUB MODEL
Home-page: https://github.com/yutiansut/QAPUBSUB
Author: yutiansut
Author-email: yutiansut@qq.com
License: MIT
Keywords: quantaxis,quant,finance,Backtest,Framework
Classifier: License :: OSI Approved :: MIT License
Classifier: Programming Language :: Python
Classifier: Intended Audience :: Developers
Classifier: Operating System :: OS Independent
Requires-Dist: pika==1.3.2
Requires-Dist: quantaxis-lance>=2.1.5a2
Requires-Dist: demjson3
Dynamic: author
Dynamic: author-email
Dynamic: classifier
Dynamic: description
Dynamic: home-page
Dynamic: keywords
Dynamic: license
Dynamic: requires-dist
Dynamic: summary
